{
  "width" : 500,
  "height" : 500,
  "depth" : 500,
  "data" : {
    "url" : "cars.json"
  },
  "mark" : "cone",
  "encoding" : {
    "x" : {
      "field" : "Weight_in_lbs",
      "type" : "quantitative"
    },
    "y" : {
      "field" : "Miles_per_Gallon",
      "type" : "quantitative"
    },
    "z" : {
      "field" : "Cylinders",
      "type" : "quantitative"
    },
    "color" : {
      "field" : "Miles_per_Gallon",
      "type" : "nominal",
      "legend" : {
        "filter" : true
      }
    }
  },
  "interaction" : [
    {
      "field" : "Cylinders",
      "type" : "toggleFilter"
    },
    {
      "field" : "Acceleration",
      "type" : "thresholdFilter"
    }
  ]
}